transforms.py
linear_transforms-0.0.2.dist-info/LICENSE
linear_transforms-0.0.2.dist-info/METADATA
linear_transforms-0.0.2.dist-info/WHEEL
linear_transforms-0.0.2.dist-info/top_level.txt
linear_transforms-0.0.2.dist-info/RECORD
